CHANGES.md
LICENSE
MANIFEST.in
README.md
numprops.py
setup.py
test_numprops.py
numprops.egg-info/PKG-INFO
numprops.egg-info/SOURCES.txt
numprops.egg-info/dependency_links.txt
numprops.egg-info/requires.txt
numprops.egg-info/top_level.txt