Metadata-Version: 1.0
Name: numprops
Version: 0.1
Summary: Numerical properties for Python objects
Home-page: https://github.com/astrofrog/numprops
Author: Thomas Robitaille
Author-email: thomas.robitaille@gmail.com
License: BSD
Platform: UNKNOWN
